Metadata-Version: 2.1
Name: cydoomgeneric
Version: 0.1.0
Summary: Easily portable doom for python
Author: Wojciech Graj
License:                     GNU GENERAL PUBLIC LICENSE
Project-URL: homepage, https://github.com/wojciech-graj/cydoomgeneric
Keywords: doom
Classifier: Development Status :: 4 - Beta
Classifier: Intended Audience :: Developers
Classifier: License :: OSI Approved :: GNU General Public License v2 or later (GPLv2+)
Classifier: Programming Language :: Python :: 3.9
Classifier: Programming Language :: Python :: 3.10
Classifier: Programming Language :: Python :: 3.11
Classifier: Programming Language :: Python :: 3.12
Classifier: Programming Language :: Python :: 3.13
Classifier: Programming Language :: Cython
Requires-Python: >=3.9
License-File: LICENSE
Requires-Dist: numpy>=1.25
Provides-Extra: dev
Requires-Dist: pylsp-mypy; extra == "dev"
Requires-Dist: pylsp-rope; extra == "dev"
Requires-Dist: python-lsp-isort; extra == "dev"
Requires-Dist: python-lsp-server[all]; extra == "dev"
Provides-Extra: pyplot
Requires-Dist: matplotlib; extra == "pyplot"
Provides-Extra: minepi
Requires-Dist: mcpi; extra == "minepi"
Requires-Dist: scikit-image; extra == "minepi"
Provides-Extra: mspaint
Requires-Dist: pyautogui; extra == "mspaint"
Requires-Dist: pywinctl; extra == "mspaint"
Requires-Dist: scikit-image; extra == "mspaint"
Provides-Extra: pygame
Requires-Dist: pygame; extra == "pygame"
